tokenrouter/__init__.py
tokenrouter/_base_client.py
tokenrouter/_client.py
tokenrouter/_compat.py
tokenrouter/_constants.py
tokenrouter/_exceptions.py
tokenrouter/_files.py
tokenrouter/_models.py
tokenrouter/_qs.py
tokenrouter/_resource.py
tokenrouter/_response.py
tokenrouter/_streaming.py
tokenrouter/_types.py
tokenrouter/_version.py
tokenrouter/py.typed
tokenrouter/_utils/__init__.py
tokenrouter/_utils/_compat.py
tokenrouter/_utils/_datetime_parse.py
tokenrouter/_utils/_logs.py
tokenrouter/_utils/_proxy.py
tokenrouter/_utils/_reflection.py
tokenrouter/_utils/_resources_proxy.py
tokenrouter/_utils/_streams.py
tokenrouter/_utils/_sync.py
tokenrouter/_utils/_transform.py
tokenrouter/_utils/_typing.py
tokenrouter/_utils/_utils.py
tokenrouter/lib/.keep
tokenrouter/resources/__init__.py
tokenrouter/resources/firewall_rules.py
tokenrouter/resources/responses.py
tokenrouter/resources/routing_rules.py
tokenrouter/types/__init__.py
tokenrouter/types/firewall_rule.py
tokenrouter/types/firewall_rule_create_params.py
tokenrouter/types/firewall_rule_create_response.py
tokenrouter/types/firewall_rule_delete_response.py
tokenrouter/types/firewall_rule_list_response.py
tokenrouter/types/firewall_rule_retrieve_response.py
tokenrouter/types/firewall_rule_update_params.py
tokenrouter/types/firewall_rule_update_response.py
tokenrouter/types/response_create_params.py
tokenrouter/types/response_object.py
tokenrouter/types/response_replay_params.py
tokenrouter/types/routing_rule.py
tokenrouter/types/routing_rule_create_params.py
tokenrouter/types/routing_rule_create_response.py
tokenrouter/types/routing_rule_delete_response.py
tokenrouter/types/routing_rule_list_response.py
tokenrouter/types/routing_rule_retrieve_response.py
tokenrouter/types/routing_rule_update_params.py
tokenrouter/types/routing_rule_update_response.py
tokenrouter-1.2.0.dist-info/METADATA
tokenrouter-1.2.0.dist-info/WHEEL
tokenrouter-1.2.0.dist-info/licenses/LICENSE
tokenrouter-1.2.0.dist-info/RECORD
